VERSION
OpenpayGrvty-0.4.8.dist-info/DESCRIPTION.rst
OpenpayGrvty-0.4.8.dist-info/METADATA
OpenpayGrvty-0.4.8.dist-info/RECORD
OpenpayGrvty-0.4.8.dist-info/WHEEL
OpenpayGrvty-0.4.8.dist-info/metadata.json
OpenpayGrvty-0.4.8.dist-info/top_level.txt
OpenpayGrvty.egg-info/PKG-INFO
OpenpayGrvty.egg-info/SOURCES.txt
OpenpayGrvty.egg-info/dependency_links.txt
OpenpayGrvty.egg-info/requires.txt
OpenpayGrvty.egg-info/top_level.txt
openpay/__init__.py
openpay/api.py
openpay/error.py
openpay/http_client.py
openpay/resource.py
openpay/util.py
openpay/version.py
openpay/__pycache__/__init__.cpython-35.pyc
openpay/__pycache__/api.cpython-35.pyc
openpay/__pycache__/error.cpython-35.pyc
openpay/__pycache__/http_client.cpython-35.pyc
openpay/__pycache__/resource.cpython-35.pyc
openpay/__pycache__/util.cpython-35.pyc
openpay/__pycache__/version.cpython-35.pyc
openpay/test/__init__.py
openpay/test/helper.py
openpay/test/test_integration.py
openpay/test/test_resources.py
