Metadata-Version: 2.0
Name: OpenpayGrvty
Version: 0.4.8
Summary: Openpay python bindings
Home-page: https://www.openpay.mx/
Author: Openpay
Author-email: soporte@openpay.mx
License: UNKNOWN
Platform: UNKNOWN
Requires-Dist: requests (>=2.1.0)
Requires-Dist: future (==0.15.2)
